Toucan_Tools-0.2.data/scripts/toucan
Toucan_Tools-0.2.data/scripts/toucan.py
tools/Polytools.py
tools/__init__.py
tools/basic.py
tools/utils.py
tools/vis.py
Toucan_Tools-0.2.dist-info/METADATA
Toucan_Tools-0.2.dist-info/WHEEL
Toucan_Tools-0.2.dist-info/top_level.txt
Toucan_Tools-0.2.dist-info/RECORD
