Metadata-Version: 2.1
Name: Toucan-Tools
Version: 0.2
Summary: A simple image processing library written in python.
Home-page: https://github.com/bm20894/Image-Tools
Author: Miles Boswell, Egan Johnson
Author-email: nunyabusiness@gmail.com
License: UNKNOWN
Platform: UNKNOWN
Classifier: Programming Language :: Python :: 3
Classifier: License :: OSI Approved :: MIT License
Classifier: Operating System :: OS Independent
